minidir/__init__.py
minidir/py.typed
minidir-0.1.3.dist-info/METADATA
minidir-0.1.3.dist-info/WHEEL
minidir-0.1.3.dist-info/RECORD
