Metadata-Version: 2.3
Name: minidir
Version: 0.1.3
Summary: Minimal directory interface and some implementations
Project-URL: Homepage, https://github.com/wdhongtw/minidir
Author-email: Weida Hong <wdhongtw@gmail.com>
Keywords: directory,fake,filesystem,testing
Classifier: License :: OSI Approved :: MIT License
Classifier: Operating System :: OS Independent
Classifier: Programming Language :: Python :: 3
Classifier: Topic :: Software Development :: Testing
Classifier: Typing :: Typed
Requires-Python: >=3.7
